comPrimos/__init__.py
comPrimos-1.0.dist-info/LICENSE
comPrimos-1.0.dist-info/METADATA
comPrimos-1.0.dist-info/WHEEL
comPrimos-1.0.dist-info/top_level.txt
comPrimos-1.0.dist-info/RECORD
