Metadata-Version: 2.1
Name: comPrimos
Version: 1.0
Summary: Una herramienta para comprobar los números primos existentes en un rango de 1 al número indicado.
Home-page: UNKNOWN
Author: Daniel Gómez del Pulgar
Author-email: dani.gdpv@gmail.com
License: GNU GPLv3
Keywords: comPrimos mathematical operations
Platform: UNKNOWN
Classifier: Development Status :: 4 - Beta
Classifier: Intended Audience :: Developers
Classifier: Topic :: Utilities
Classifier: License :: OSI Approved :: GNU General Public License v3 (GPLv3)
Classifier: Programming Language :: Python :: 3
Classifier: Operating System :: OS Independent
License-File: LICENSE
